<?xml version="1.0" encoding="utf-8" ?>

<Patch>
  
   <Operation Class="PatchOperationAddModExtension">
    <xpath>/Defs/PawnKindDef[defName="USCMPrivate"]</xpath>
    <value>
      <li Class="CombatExtended.LoadoutPropertiesExtension">
        <primaryMagazineCount>
          <min>3</min>
          <max>5</max>
        </primaryMagazineCount>
        <forcedSidearm>
          <sidearmMoney>
            <min>800</min>
            <max>1200</max>
          </sidearmMoney>
          <weaponTags>
            <li>NonNeolithicOnlyMelee</li>
          </weaponTags>
          <magazineCount>
            <min>3</min>
            <max>5</max>
          </magazineCount>
        </forcedSidearm>
      </li>
    </value>
  </Operation>
  
  <Operation Class="PatchOperationAddModExtension">
    <xpath>/Defs/PawnKindDef[defName="USCMPrivateFirstClassArtillery"]</xpath>
    <value>
      <li Class="CombatExtended.LoadoutPropertiesExtension">
        <primaryMagazineCount>
          <min>3</min>
          <max>5</max>
        </primaryMagazineCount>
        <forcedSidearm>
          <sidearmMoney>
            <min>800</min>
            <max>1500</max>
          </sidearmMoney>
          <weaponTags>
            <li>NonNeolithicOnlyMelee</li>
          </weaponTags>
          <magazineCount>
            <min>3</min>
            <max>5</max>
          </magazineCount>
        </forcedSidearm>
      </li>
    </value>
  </Operation>
  
  <Operation Class="PatchOperationAddModExtension">
    <xpath>/Defs/PawnKindDef[defName="USCMPrivateFirstClassSniper"]</xpath>
    <value>
      <li Class="CombatExtended.LoadoutPropertiesExtension">
        <primaryMagazineCount>
          <min>4</min>
          <max>5</max>
        </primaryMagazineCount>
        <forcedSidearm>
          <sidearmMoney>
            <min>800</min>
            <max>1500</max>
          </sidearmMoney>
          <weaponTags>
            <li>NonNeolithicOnlyMelee</li>
          </weaponTags>
          <magazineCount>
            <min>3</min>
            <max>5</max>
          </magazineCount>
        </forcedSidearm>
      </li>
    </value>
  </Operation>
  
  <Operation Class="PatchOperationAddModExtension">
    <xpath>/Defs/PawnKindDef[defName="USCMPrivateFirstClassBurner"]</xpath>
    <value>
      <li Class="CombatExtended.LoadoutPropertiesExtension">
        <primaryMagazineCount>
          <min>3</min>
          <max>5</max>
        </primaryMagazineCount>
        <forcedSidearm>
          <sidearmMoney>
            <min>800</min>
            <max>1500</max>
          </sidearmMoney>
          <weaponTags>
            <li>NonNeolithicOnlyMelee</li>
          </weaponTags>
          <magazineCount>
            <min>3</min>
            <max>5</max>
          </magazineCount>
        </forcedSidearm>
      </li>
    </value>
  </Operation>
  
  <Operation Class="PatchOperationAddModExtension">
    <xpath>/Defs/PawnKindDef[defName="USCMLanceCorporal"]</xpath>
    <value>
      <li Class="CombatExtended.LoadoutPropertiesExtension">
        <primaryMagazineCount>
          <min>3</min>
          <max>5</max>
        </primaryMagazineCount>
        <forcedSidearm>
          <sidearmMoney>
            <min>1500</min>
            <max>2000</max>
          </sidearmMoney>
          <weaponTags>
            <li>NonNeolithicOnlyMelee</li>
          </weaponTags>
        </forcedSidearm>
		  <magazineCount>
            <min>3</min>
            <max>5</max>
          </magazineCount>
      </li>
    </value>
  </Operation>
  
  <Operation Class="PatchOperationAddModExtension">
    <xpath>/Defs/PawnKindDef[defName="USCMCorporal"]</xpath>
    <value>
      <li Class="CombatExtended.LoadoutPropertiesExtension">
        <primaryMagazineCount>
          <min>3</min>
          <max>5</max>
        </primaryMagazineCount>
        <forcedSidearm>
          <sidearmMoney>
            <min>1800</min>
            <max>2400</max>
          </sidearmMoney>
          <weaponTags>
            <li>NonNeolithicOnlyMelee</li>
          </weaponTags>
          <magazineCount>
            <min>3</min>
            <max>5</max>
          </magazineCount>
        </forcedSidearm>
      </li>
    </value>
  </Operation>
  
</Patch>